{
  "schema_version": "course_rules_v1",
  "generatedAt": "2026-07-14T15:31:43.463866+00:00",
  "dataDate": "2026-07-13",
  "article": {
    "title": "Trade Journal",
    "date": "July 13, 2026",
    "url": "https://www.tradingforbj.com/products/bj-trading-journal/categories/2159892046/posts/2198784606"
  },
  "summary": {
    "entry_confirmed": 0,
    "watchlist": 0,
    "needs_evidence": 0,
    "not_eligible": 3,
    "unavailable": 0,
    "activeCount": 3,
    "alerts": 0
  },
  "rankings": [
    {
      "ticker": "MU",
      "company": "Micron Technology",
      "membership": {
        "ticker": "MU",
        "company": "Micron Technology",
        "active": true,
        "bjStatus": "new_watchlist",
        "addedArticleDate": "July 13, 2026",
        "lastSeenArticleDate": "July 13, 2026",
        "stale": false
      },
      "dataDate": "2026-07-13",
      "schemaVersion": "course_rules_v1",
      "lesson3": {
        "schemaVersion": "course_rules_v1",
        "symbol": "MU",
        "availability": "available",
        "dataDate": "2026-07-13",
        "overallStatus": "not_eligible",
        "overallLabel": "Not eligible",
        "reasons": [
          "Price is 25.3% below the high.",
          "Official or manually verified RS Rating evidence is unavailable.",
          "Pattern candidate requires manual chart confirmation."
        ],
        "stage2": {
          "overall": "fail",
          "checks": [
            {
              "status": "pass",
              "label": "Price above 150MA and 200MA",
              "evidence": "937.00 is above both averages.",
              "value": true
            },
            {
              "status": "pass",
              "label": "150MA above 200MA",
              "evidence": "150MA is above 200MA.",
              "value": true
            },
            {
              "status": "pass",
              "label": "200MA rising for about one month",
              "evidence": "Current 200MA is above its value 20 sessions ago.",
              "value": true
            },
            {
              "status": "pass",
              "label": "50MA above 150MA and 200MA",
              "evidence": "50MA > 150MA > 200MA.",
              "value": true
            },
            {
              "status": "fail",
              "label": "Within about 25% of 52-week high",
              "evidence": "Price is 25.3% below the high.",
              "value": false
            },
            {
              "status": "pass",
              "label": "At least about 25% above 52-week low",
              "evidence": "Price is 806.4% above the low.",
              "value": true
            },
            {
              "status": "unknown",
              "label": "RS Rating above 70 and rising for about six weeks",
              "evidence": "Official or manually verified RS Rating evidence is unavailable.",
              "value": null
            },
            {
              "status": "pending",
              "label": "Above 50MA when leaving the base",
              "evidence": "Price has not closed above the candidate resistance.",
              "value": null
            }
          ],
          "indicators": {
            "currentPrice": 937.0,
            "ma50": 907.42,
            "ma150": 554.06,
            "ma200": 468.34,
            "ma200TwentySessionsAgo": 377.38,
            "high52Week": 1255.0,
            "low52Week": 103.38,
            "distanceFromHighPct": -25.34,
            "aboveLowPct": 806.36,
            "rsRating": null,
            "rsRisingSixWeeks": null
          }
        },
        "pattern": {
          "confirmation": "unknown",
          "confirmedType": null,
          "candidateType": "Cup without Handle",
          "candidates": [
            {
              "name": "Cup without Handle",
              "status": "candidate",
              "confirmation": "unknown",
              "windowSessions": 90,
              "depthPct": 75.18,
              "notes": [
                "Cup depth 33.9%; recovered to 198.8% of the rim."
              ],
              "cupDepthPct": 33.91,
              "priorAdvancePct": 99.51
            },
            {
              "name": "Saucer with Handle",
              "status": "not_observed",
              "confirmation": "unknown",
              "windowSessions": 65,
              "depthPct": 68.25,
              "notes": [
                "Long rounded base depth 68.3%; handle 23.7%."
              ],
              "handleDepthPct": 23.7
            },
            {
              "name": "VCP",
              "status": "not_observed",
              "confirmation": "unknown",
              "windowSessions": 35,
              "depthPct": 41.66,
              "notes": [
                "A complete contraction sequence was not observed."
              ],
              "pullbackDepthsPct": [
                6.9,
                18.33,
                18.43,
                28.95
              ]
            },
            {
              "name": "Cup and Handle",
              "status": "not_observed",
              "confirmation": "unknown",
              "windowSessions": 35,
              "depthPct": 41.66,
              "notes": [
                "Cup 36.3%; handle 29.0%; prior advance 207.0%."
              ],
              "cupDepthPct": 36.3,
              "handleDepthPct": 28.95,
              "handleSessions": 15,
              "priorAdvancePct": 206.96
            },
            {
              "name": "Double Bottom",
              "status": "not_observed",
              "confirmation": "unknown",
              "windowSessions": 35,
              "depthPct": 41.66,
              "notes": [
                "No complete W-shaped candidate observed."
              ],
              "troughs": null
            }
          ]
        },
        "pivot": 1255.0,
        "distanceToPivotPct": -25.34,
        "breakoutEvidence": {
          "intradayCrossObserved": false,
          "closeAbovePivot": false,
          "volumeRatio50": 0.65,
          "lessonExamplePlus50Pct": false,
          "note": "The lesson shows roughly +50% breakout volume as an example; it is evidence, not an invented hard gate."
        },
        "entryMethods": [
          {
            "id": "breakout_immediate",
            "label": "Buy on breakout",
            "status": "pending",
            "evidence": "No daily high above candidate resistance."
          },
          {
            "id": "end_of_day",
            "label": "Buy near end of day",
            "status": "pending",
            "evidence": "Await a daily close above candidate resistance.",
            "modelDefault": true
          },
          {
            "id": "pullback_reversal",
            "label": "Pullback and reversal",
            "status": "pending",
            "evidence": "No complete breakout-retest-reversal sequence observed."
          }
        ],
        "screeningEvidence": [
          {
            "status": "unknown",
            "label": "Sales growth",
            "evidence": "No verified evidence supplied.",
            "value": null
          },
          {
            "status": "unknown",
            "label": "EPS growth",
            "evidence": "No verified evidence supplied.",
            "value": null
          },
          {
            "status": "unknown",
            "label": "Industry strength",
            "evidence": "No verified evidence supplied.",
            "value": null
          },
          {
            "status": "unknown",
            "label": "Stock story reviewed",
            "evidence": "No verified evidence supplied.",
            "value": null
          }
        ]
      },
      "lesson4ModelPlan": {
        "schemaVersion": "course_rules_v1",
        "kind": "model_plan",
        "availability": "available",
        "disclaimer": "Public educational model plan only; not an actual holding, live alert or order.",
        "assumptions": {
          "entryAtPivot": true,
          "maxRiskUsd": 250.0,
          "defaultBuyMethod": "end_of_day"
        },
        "feasible": false,
        "entryPrice": 1255.0,
        "initialStop": 891.66,
        "supportEvidence": "Most recent local low on 2026-07-07.",
        "stopDistancePct": 28.95,
        "riskPerShare": 363.34,
        "quantitySuggested": null,
        "plannedMaxLossUsd": null,
        "targets": {
          "oneR": 1618.34,
          "twoR": 1981.68,
          "threeR": 2345.02,
          "partialExitAllocation": "unknown"
        },
        "monitoring": {
          "asOf": "2026-07-13",
          "dailyCloseOnly": true,
          "ma20": 1050.62,
          "lowerLows": [
            991.1,
            1023.65,
            891.66
          ]
        },
        "stageMaturity": {
          "status": "unknown",
          "baseCount": null,
          "evidence": "No verified early/late-stage evidence supplied."
        },
        "sellIntoWeakness": {
          "courseUse": "Early Stage 2: allow normal pullbacks and sell when weakness is actually observed.",
          "signals": [
            {
              "status": "pass",
              "label": "Close below 20MA",
              "evidence": "Latest close is below 20MA.",
              "value": true
            },
            {
              "status": "fail",
              "label": "Three lower lows",
              "evidence": "The latest three local lows are not descending.",
              "value": false
            },
            {
              "status": "pending",
              "label": "Initial stop / support breach",
              "evidence": "Model stop has not been reached.",
              "value": null
            },
            {
              "status": "unknown",
              "label": "Price and volume deterioration",
              "evidence": "The lesson gives no fixed threshold; review the displayed OHLCV evidence manually.",
              "value": null
            },
            {
              "status": "unknown",
              "label": "Earnings risk",
              "evidence": "Verified earnings date unavailable.",
              "value": null
            }
          ]
        },
        "sellIntoStrength": {
          "courseUse": "Late-stage market or stock: consider realizing gains into strength and resistance.",
          "levels": {
            "oneR": 1618.34,
            "twoR": 1981.68,
            "threeR": 2345.02,
            "chartResistance": "unknown"
          },
          "climaxSignals": [
            {
              "status": "unknown",
              "label": "Correction volume exceeds every post-breakout day",
              "evidence": "No completed model breakout history.",
              "value": null
            },
            {
              "status": "unknown",
              "label": "Unusually high volume without matching price progress",
              "evidence": "No verified event/chart judgement supplied.",
              "value": null
            },
            {
              "status": "unknown",
              "label": "Longest daily candle since breakout",
              "evidence": "No completed model breakout history.",
              "value": null
            }
          ],
          "positiveNewsNegativeReaction": {
            "status": "unknown",
            "label": "Positive news with negative price action",
            "evidence": "No verified news-reaction evidence supplied.",
            "value": null
          }
        },
        "notes": [
          "Technical stop is wider than 10%; this model entry is not feasible and no position size is suggested.",
          "Verified earnings date unavailable; earnings risk remains Unknown."
        ]
      }
    },
    {
      "ticker": "ALAB",
      "company": "Astera Labs",
      "membership": {
        "ticker": "ALAB",
        "company": "Astera Labs",
        "active": true,
        "bjStatus": "new_watchlist",
        "addedArticleDate": "July 13, 2026",
        "lastSeenArticleDate": "July 13, 2026",
        "stale": false
      },
      "dataDate": "2026-07-13",
      "schemaVersion": "course_rules_v1",
      "lesson3": {
        "schemaVersion": "course_rules_v1",
        "symbol": "ALAB",
        "availability": "available",
        "dataDate": "2026-07-13",
        "overallStatus": "not_eligible",
        "overallLabel": "Not eligible",
        "reasons": [
          "Price is 27.5% below the high.",
          "Official or manually verified RS Rating evidence is unavailable.",
          "Pattern candidate requires manual chart confirmation."
        ],
        "stage2": {
          "overall": "fail",
          "checks": [
            {
              "status": "pass",
              "label": "Price above 150MA and 200MA",
              "evidence": "362.05 is above both averages.",
              "value": true
            },
            {
              "status": "pass",
              "label": "150MA above 200MA",
              "evidence": "150MA is above 200MA.",
              "value": true
            },
            {
              "status": "pass",
              "label": "200MA rising for about one month",
              "evidence": "Current 200MA is above its value 20 sessions ago.",
              "value": true
            },
            {
              "status": "pass",
              "label": "50MA above 150MA and 200MA",
              "evidence": "50MA > 150MA > 200MA.",
              "value": true
            },
            {
              "status": "fail",
              "label": "Within about 25% of 52-week high",
              "evidence": "Price is 27.5% below the high.",
              "value": false
            },
            {
              "status": "pass",
              "label": "At least about 25% above 52-week low",
              "evidence": "Price is 310.6% above the low.",
              "value": true
            },
            {
              "status": "unknown",
              "label": "RS Rating above 70 and rising for about six weeks",
              "evidence": "Official or manually verified RS Rating evidence is unavailable.",
              "value": null
            },
            {
              "status": "pending",
              "label": "Above 50MA when leaving the base",
              "evidence": "Price has not closed above the candidate resistance.",
              "value": null
            }
          ],
          "indicators": {
            "currentPrice": 362.05,
            "ma50": 328.47,
            "ma150": 209.65,
            "ma200": 200.42,
            "ma200TwentySessionsAgo": 181.19,
            "high52Week": 499.48,
            "low52Week": 88.19,
            "distanceFromHighPct": -27.51,
            "aboveLowPct": 310.56,
            "rsRating": null,
            "rsRisingSixWeeks": null
          }
        },
        "pattern": {
          "confirmation": "unknown",
          "confirmedType": null,
          "candidateType": "Cup without Handle",
          "candidates": [
            {
              "name": "Cup without Handle",
              "status": "candidate",
              "confirmation": "unknown",
              "windowSessions": 90,
              "depthPct": 80.4,
              "notes": [
                "Cup depth 27.6%; recovered to 267.8% of the rim."
              ],
              "cupDepthPct": 27.59,
              "priorAdvancePct": 80.11
            },
            {
              "name": "Double Bottom",
              "status": "candidate",
              "confirmation": "unknown",
              "windowSessions": 65,
              "depthPct": 75.27,
              "notes": [
                "Two similar lows with recovery toward intervening resistance."
              ],
              "troughs": [
                179.54,
                189.69
              ]
            },
            {
              "name": "Saucer with Handle",
              "status": "not_observed",
              "confirmation": "unknown",
              "windowSessions": 65,
              "depthPct": 75.27,
              "notes": [
                "Long rounded base depth 72.0%; handle 29.9%."
              ],
              "handleDepthPct": 29.91
            },
            {
              "name": "VCP",
              "status": "not_observed",
              "confirmation": "unknown",
              "windowSessions": 35,
              "depthPct": 43.56,
              "notes": [
                "A complete contraction sequence was not observed."
              ],
              "pullbackDepthsPct": [
                10.87,
                18.63,
                15.53,
                26.59
              ]
            },
            {
              "name": "Cup and Handle",
              "status": "not_observed",
              "confirmation": "unknown",
              "windowSessions": 25,
              "depthPct": 39.34,
              "notes": [
                "Cup 31.3%; handle 29.9%; prior advance 280.4%."
              ],
              "cupDepthPct": 31.29,
              "handleDepthPct": 29.91,
              "handleSessions": 10,
              "priorAdvancePct": 280.4
            }
          ]
        },
        "pivot": 499.48,
        "distanceToPivotPct": -27.51,
        "breakoutEvidence": {
          "intradayCrossObserved": false,
          "closeAbovePivot": false,
          "volumeRatio50": 1.02,
          "lessonExamplePlus50Pct": false,
          "note": "The lesson shows roughly +50% breakout volume as an example; it is evidence, not an invented hard gate."
        },
        "entryMethods": [
          {
            "id": "breakout_immediate",
            "label": "Buy on breakout",
            "status": "pending",
            "evidence": "No daily high above candidate resistance."
          },
          {
            "id": "end_of_day",
            "label": "Buy near end of day",
            "status": "pending",
            "evidence": "Await a daily close above candidate resistance.",
            "modelDefault": true
          },
          {
            "id": "pullback_reversal",
            "label": "Pullback and reversal",
            "status": "pending",
            "evidence": "No complete breakout-retest-reversal sequence observed."
          }
        ],
        "screeningEvidence": [
          {
            "status": "unknown",
            "label": "Sales growth",
            "evidence": "No verified evidence supplied.",
            "value": null
          },
          {
            "status": "unknown",
            "label": "EPS growth",
            "evidence": "No verified evidence supplied.",
            "value": null
          },
          {
            "status": "unknown",
            "label": "Industry strength",
            "evidence": "No verified evidence supplied.",
            "value": null
          },
          {
            "status": "unknown",
            "label": "Stock story reviewed",
            "evidence": "No verified evidence supplied.",
            "value": null
          }
        ]
      },
      "lesson4ModelPlan": {
        "schemaVersion": "course_rules_v1",
        "kind": "model_plan",
        "availability": "available",
        "disclaimer": "Public educational model plan only; not an actual holding, live alert or order.",
        "assumptions": {
          "entryAtPivot": true,
          "maxRiskUsd": 250.0,
          "defaultBuyMethod": "end_of_day"
        },
        "feasible": false,
        "entryPrice": 499.48,
        "initialStop": 366.66,
        "supportEvidence": "Most recent local low on 2026-07-07.",
        "stopDistancePct": 26.59,
        "riskPerShare": 132.82,
        "quantitySuggested": null,
        "plannedMaxLossUsd": null,
        "targets": {
          "oneR": 632.3,
          "twoR": 765.12,
          "threeR": 897.94,
          "partialExitAllocation": "unknown"
        },
        "monitoring": {
          "asOf": "2026-07-13",
          "dailyCloseOnly": true,
          "ma20": 405.68,
          "lowerLows": [
            303.0,
            372.5,
            366.66
          ]
        },
        "stageMaturity": {
          "status": "unknown",
          "baseCount": null,
          "evidence": "No verified early/late-stage evidence supplied."
        },
        "sellIntoWeakness": {
          "courseUse": "Early Stage 2: allow normal pullbacks and sell when weakness is actually observed.",
          "signals": [
            {
              "status": "pass",
              "label": "Close below 20MA",
              "evidence": "Latest close is below 20MA.",
              "value": true
            },
            {
              "status": "fail",
              "label": "Three lower lows",
              "evidence": "The latest three local lows are not descending.",
              "value": false
            },
            {
              "status": "pass",
              "label": "Initial stop / support breach",
              "evidence": "Latest daily low reached the model stop.",
              "value": null
            },
            {
              "status": "unknown",
              "label": "Price and volume deterioration",
              "evidence": "The lesson gives no fixed threshold; review the displayed OHLCV evidence manually.",
              "value": null
            },
            {
              "status": "unknown",
              "label": "Earnings risk",
              "evidence": "Verified earnings date unavailable.",
              "value": null
            }
          ]
        },
        "sellIntoStrength": {
          "courseUse": "Late-stage market or stock: consider realizing gains into strength and resistance.",
          "levels": {
            "oneR": 632.3,
            "twoR": 765.12,
            "threeR": 897.94,
            "chartResistance": "unknown"
          },
          "climaxSignals": [
            {
              "status": "unknown",
              "label": "Correction volume exceeds every post-breakout day",
              "evidence": "No completed model breakout history.",
              "value": null
            },
            {
              "status": "unknown",
              "label": "Unusually high volume without matching price progress",
              "evidence": "No verified event/chart judgement supplied.",
              "value": null
            },
            {
              "status": "unknown",
              "label": "Longest daily candle since breakout",
              "evidence": "No completed model breakout history.",
              "value": null
            }
          ],
          "positiveNewsNegativeReaction": {
            "status": "unknown",
            "label": "Positive news with negative price action",
            "evidence": "No verified news-reaction evidence supplied.",
            "value": null
          }
        },
        "notes": [
          "Technical stop is wider than 10%; this model entry is not feasible and no position size is suggested.",
          "Verified earnings date unavailable; earnings risk remains Unknown."
        ]
      }
    },
    {
      "ticker": "SPCX",
      "company": "Space Exploration Technologies",
      "membership": {
        "ticker": "SPCX",
        "company": "Space Exploration Technologies",
        "active": true,
        "bjStatus": "new_watchlist",
        "addedArticleDate": "July 13, 2026",
        "lastSeenArticleDate": "July 13, 2026",
        "stale": false
      },
      "dataDate": "2026-07-13",
      "schemaVersion": "course_rules_v1",
      "lesson3": {
        "schemaVersion": "course_rules_v1",
        "symbol": "SPCX",
        "availability": "available",
        "dataDate": "2026-07-13",
        "overallStatus": "not_eligible",
        "overallLabel": "Not eligible",
        "reasons": [
          "150MA or 200MA unavailable.",
          "150MA or 200MA unavailable.",
          "At least 220 sessions are required.",
          "Required averages unavailable.",
          "Price is 38.3% below the high.",
          "Price is only 1.7% above the low.",
          "Official or manually verified RS Rating evidence is unavailable.",
          "Pivot or 50MA unavailable.",
          "Pattern candidate requires manual chart confirmation."
        ],
        "stage2": {
          "overall": "fail",
          "checks": [
            {
              "status": "unknown",
              "label": "Price above 150MA and 200MA",
              "evidence": "150MA or 200MA unavailable.",
              "value": null
            },
            {
              "status": "unknown",
              "label": "150MA above 200MA",
              "evidence": "150MA or 200MA unavailable.",
              "value": null
            },
            {
              "status": "unknown",
              "label": "200MA rising for about one month",
              "evidence": "At least 220 sessions are required.",
              "value": null
            },
            {
              "status": "unknown",
              "label": "50MA above 150MA and 200MA",
              "evidence": "Required averages unavailable.",
              "value": null
            },
            {
              "status": "fail",
              "label": "Within about 25% of 52-week high",
              "evidence": "Price is 38.3% below the high.",
              "value": false
            },
            {
              "status": "fail",
              "label": "At least about 25% above 52-week low",
              "evidence": "Price is only 1.7% above the low.",
              "value": false
            },
            {
              "status": "unknown",
              "label": "RS Rating above 70 and rising for about six weeks",
              "evidence": "Official or manually verified RS Rating evidence is unavailable.",
              "value": null
            },
            {
              "status": "unknown",
              "label": "Above 50MA when leaving the base",
              "evidence": "Pivot or 50MA unavailable.",
              "value": null
            }
          ],
          "indicators": {
            "currentPrice": 139.14,
            "ma50": null,
            "ma150": null,
            "ma200": null,
            "ma200TwentySessionsAgo": null,
            "high52Week": 225.64,
            "low52Week": 136.78,
            "distanceFromHighPct": -38.34,
            "aboveLowPct": 1.73,
            "rsRating": null,
            "rsRisingSixWeeks": null
          }
        },
        "pattern": {
          "confirmation": "unknown",
          "confirmedType": null,
          "candidateType": null,
          "candidates": []
        },
        "pivot": 225.64,
        "distanceToPivotPct": -38.34,
        "breakoutEvidence": {
          "intradayCrossObserved": false,
          "closeAbovePivot": false,
          "volumeRatio50": 0.48,
          "lessonExamplePlus50Pct": false,
          "note": "The lesson shows roughly +50% breakout volume as an example; it is evidence, not an invented hard gate."
        },
        "entryMethods": [
          {
            "id": "breakout_immediate",
            "label": "Buy on breakout",
            "status": "pending",
            "evidence": "No daily high above candidate resistance."
          },
          {
            "id": "end_of_day",
            "label": "Buy near end of day",
            "status": "pending",
            "evidence": "Await a daily close above candidate resistance.",
            "modelDefault": true
          },
          {
            "id": "pullback_reversal",
            "label": "Pullback and reversal",
            "status": "pending",
            "evidence": "No complete breakout-retest-reversal sequence observed."
          }
        ],
        "screeningEvidence": [
          {
            "status": "unknown",
            "label": "Sales growth",
            "evidence": "No verified evidence supplied.",
            "value": null
          },
          {
            "status": "unknown",
            "label": "EPS growth",
            "evidence": "No verified evidence supplied.",
            "value": null
          },
          {
            "status": "unknown",
            "label": "Industry strength",
            "evidence": "No verified evidence supplied.",
            "value": null
          },
          {
            "status": "unknown",
            "label": "Stock story reviewed",
            "evidence": "No verified evidence supplied.",
            "value": null
          }
        ]
      },
      "lesson4ModelPlan": {
        "schemaVersion": "course_rules_v1",
        "kind": "model_plan",
        "availability": "available",
        "disclaimer": "Public educational model plan only; not an actual holding, live alert or order.",
        "assumptions": {
          "entryAtPivot": true,
          "maxRiskUsd": 250.0,
          "defaultBuyMethod": "end_of_day"
        },
        "feasible": false,
        "entryPrice": 225.64,
        "initialStop": 148.51,
        "supportEvidence": "Most recent local low on 2026-06-26.",
        "stopDistancePct": 34.18,
        "riskPerShare": 77.13,
        "quantitySuggested": null,
        "plannedMaxLossUsd": null,
        "targets": {
          "oneR": 302.77,
          "twoR": 379.9,
          "threeR": 457.03,
          "partialExitAllocation": "unknown"
        },
        "monitoring": {
          "asOf": "2026-07-13",
          "dailyCloseOnly": true,
          "ma20": 162.65,
          "lowerLows": [
            147.11,
            148.51
          ]
        },
        "stageMaturity": {
          "status": "unknown",
          "baseCount": null,
          "evidence": "No verified early/late-stage evidence supplied."
        },
        "sellIntoWeakness": {
          "courseUse": "Early Stage 2: allow normal pullbacks and sell when weakness is actually observed.",
          "signals": [
            {
              "status": "pass",
              "label": "Close below 20MA",
              "evidence": "Latest close is below 20MA.",
              "value": true
            },
            {
              "status": "unknown",
              "label": "Three lower lows",
              "evidence": "Fewer than three confirmed local lows.",
              "value": null
            },
            {
              "status": "pass",
              "label": "Initial stop / support breach",
              "evidence": "Latest daily low reached the model stop.",
              "value": null
            },
            {
              "status": "unknown",
              "label": "Price and volume deterioration",
              "evidence": "The lesson gives no fixed threshold; review the displayed OHLCV evidence manually.",
              "value": null
            },
            {
              "status": "unknown",
              "label": "Earnings risk",
              "evidence": "Verified earnings date unavailable.",
              "value": null
            }
          ]
        },
        "sellIntoStrength": {
          "courseUse": "Late-stage market or stock: consider realizing gains into strength and resistance.",
          "levels": {
            "oneR": 302.77,
            "twoR": 379.9,
            "threeR": 457.03,
            "chartResistance": "unknown"
          },
          "climaxSignals": [
            {
              "status": "unknown",
              "label": "Correction volume exceeds every post-breakout day",
              "evidence": "No completed model breakout history.",
              "value": null
            },
            {
              "status": "unknown",
              "label": "Unusually high volume without matching price progress",
              "evidence": "No verified event/chart judgement supplied.",
              "value": null
            },
            {
              "status": "unknown",
              "label": "Longest daily candle since breakout",
              "evidence": "No completed model breakout history.",
              "value": null
            }
          ],
          "positiveNewsNegativeReaction": {
            "status": "unknown",
            "label": "Positive news with negative price action",
            "evidence": "No verified news-reaction evidence supplied.",
            "value": null
          }
        },
        "notes": [
          "Technical stop is wider than 10%; this model entry is not feasible and no position size is suggested.",
          "Verified earnings date unavailable; earnings risk remains Unknown."
        ]
      }
    }
  ],
  "alerts": [],
  "methodology": "Lesson 3 pass/fail/unknown checks plus Lesson 4 public model plans. No numeric score or rating.",
  "disclaimer": "Public educational model plans only; not actual holdings, live alerts or personalized investment advice."
}
